yeledeploy/__init__.py
yeledeploy/cli.py
yeledeploy/database.py
yeledeploy/deployment.py
yeledeploy/utils.py
yeledeploy-1.0.0.dist-info/licenses/LICENCE
yeledeploy-1.0.0.dist-info/METADATA
yeledeploy-1.0.0.dist-info/WHEEL
yeledeploy-1.0.0.dist-info/entry_points.txt
yeledeploy-1.0.0.dist-info/top_level.txt
yeledeploy-1.0.0.dist-info/RECORD
