Metadata-Version: 2.4
Name: yeledeploy
Version: 1.0.0
Summary: Automated Django deployment tool for EC2 with PostgreSQL, Nginx, and Gunicorn
Home-page: https://github.com/chrisokoth/ops-toolkit/yeledeploy
Author: Your Name
Author-email: Chris Okoth <chris@yelegroup.africa>
License: MIT
Project-URL: Homepage, https://github.com/chrisokoth/ops-toolkit/yeledeploy
Project-URL: Repository, https://github.com/chrisokoth/ops-toolkit/yeledeploy
Project-URL: Issues, https://github.com/chrisokoth/ops-toolkit/yeledeploy/issues
Classifier: Development Status :: 4 - Beta
Classifier: Intended Audience :: Developers
Classifier: License :: OSI Approved :: MIT License
Classifier: Operating System :: POSIX :: Linux
Classifier: Programming Language :: Python :: 3
Classifier: Programming Language :: Python :: 3.8
Classifier: Programming Language :: Python :: 3.9
Classifier: Programming Language :: Python :: 3.10
Classifier: Programming Language :: Python :: 3.11
Classifier: Topic :: Software Development :: Build Tools
Classifier: Topic :: System :: Installation/Setup
Requires-Python: >=3.8
License-File: LICENCE
Requires-Dist: click>=8.0.0
Requires-Dist: colorama>=0.4.0
Requires-Dist: psycopg2-binary>=2.9.0
Requires-Dist: jinja2>=3.0.0
Requires-Dist: django>=3.2.0
Dynamic: author
Dynamic: home-page
Dynamic: license-file
Dynamic: requires-python
